READ_pytorch/__init__.py
READ_pytorch/version.py
READ_pytorch/ad_algorithm/_FAVAE.py
READ_pytorch/ad_algorithm/_Intra.py
READ_pytorch/ad_algorithm/_PaDiM.py
READ_pytorch/ad_algorithm/_RIAD.py
READ_pytorch/ad_algorithm/_SPADE.py
READ_pytorch/ad_algorithm/_STPM.py
READ_pytorch/ad_algorithm/_SemiOrth.py
READ_pytorch/ad_algorithm/_USTAD.py
READ_pytorch/ad_algorithm/__init__.py
READ_pytorch/backbones/__init__.py
READ_pytorch/backbones/_resnet.py
READ_pytorch/backbones/_senet.py
READ_pytorch/datasets/__init__.py
READ_pytorch/datasets/_imagenet.py
READ_pytorch/datasets/_mvtec.py
READ_pytorch/datasets/_transformations.py
READ_pytorch/losses/__init__.py
READ_pytorch/losses/_gms_loss.py
READ_pytorch/losses/_ssim_loss.py
READ_pytorch/optimizer/__init__.py
READ_pytorch/optimizer/_optimizer.py
READ_pytorch/scheduler/__init__.py
READ_pytorch/scheduler/_scheduler.py
READ_pytorch/utils/__init__.py
READ_pytorch/utils/_checkpoint_helper.py
READ_pytorch/utils/_gpu_manager.py
READ_pytorch/utils/_image_helper.py
READ_pytorch/utils/_log.py
READ_pytorch/utils/_metrics.py
READ_pytorch-0.1.1.dist-info/LICENSE
READ_pytorch-0.1.1.dist-info/METADATA
READ_pytorch-0.1.1.dist-info/WHEEL
READ_pytorch-0.1.1.dist-info/top_level.txt
READ_pytorch-0.1.1.dist-info/RECORD
